zeraora/__init__.py
zeraora/converters.py
zeraora/generators.py
zeraora/gvs.py
zeraora/structures.py
zeraora/throwables.py
zeraora/typeclasses.py
zeraora/utils.py
zeraora/click/__init__.py
zeraora/click/decorators.py
zeraora/constants/__init__.py
zeraora/constants/charsets.py
zeraora/constants/configs.py
zeraora/constants/enumerations.py
zeraora/dj/__init__.py
zeraora/dj/fields.py
zeraora/dj/lookups.py
zeraora/dj/models.py
zeraora/drf/__init__.py
zeraora/drf/filters.py
zeraora/drf/viewsets.py
Zeraora-0.3.5.dist-info/LICENSE
Zeraora-0.3.5.dist-info/METADATA
Zeraora-0.3.5.dist-info/WHEEL
Zeraora-0.3.5.dist-info/top_level.txt
Zeraora-0.3.5.dist-info/RECORD
