Metadata-Version: 2.1
Name: Zeraora
Version: 0.3.5
Summary: 为了跨平台跨项目复用代码而开发的工具库。A utility Python package for our personal and corporate projects, with long time support.
Home-page: https://github.com/aixcyi/zeraora
Author: aixcyi
Author-email: 75880483+aixcyi@users.noreply.github.com
License: MIT
Project-URL: Source, https://github.com/aixcyi/zeraora
Project-URL: Tracker, https://github.com/aixcyi/zeraora/issues
Platform: UNKNOWN
Classifier: Development Status :: 4 - Beta
Classifier: Programming Language :: Python :: 3
Classifier: Programming Language :: Python :: 3.7
Classifier: Programming Language :: Python :: 3.8
Classifier: Programming Language :: Python :: 3.9
Classifier: Programming Language :: Python :: 3.10
Classifier: Programming Language :: Python :: 3.11
Classifier: Programming Language :: Python :: 3.12
Classifier: Intended Audience :: Developers
Classifier: Operating System :: OS Independent
Classifier: Natural Language :: Chinese (Simplified)
Classifier: License :: OSI Approved :: MIT License
Classifier: Topic :: Utilities
Classifier: Typing :: Typed
Requires-Python: >=3.7
